jitxcore/__init__.py
jitxcore/version.py
jitxcore/_proto/__init__.py
jitxcore/_proto/board_pb2.py
jitxcore/_proto/board_pb2.pyi
jitxcore/_proto/bundle_pb2.py
jitxcore/_proto/bundle_pb2.pyi
jitxcore/_proto/component_pb2.py
jitxcore/_proto/component_pb2.pyi
jitxcore/_proto/design_pb2.py
jitxcore/_proto/design_pb2.pyi
jitxcore/_proto/design_rules_pb2.py
jitxcore/_proto/design_rules_pb2.pyi
jitxcore/_proto/diff_routing_pb2.py
jitxcore/_proto/diff_routing_pb2.pyi
jitxcore/_proto/enums_pb2.py
jitxcore/_proto/enums_pb2.pyi
jitxcore/_proto/file_info_pb2.py
jitxcore/_proto/file_info_pb2.pyi
jitxcore/_proto/geom_pb2.py
jitxcore/_proto/geom_pb2.pyi
jitxcore/_proto/instances_pb2.py
jitxcore/_proto/instances_pb2.pyi
jitxcore/_proto/landpattern_pb2.py
jitxcore/_proto/landpattern_pb2.pyi
jitxcore/_proto/layers_pb2.py
jitxcore/_proto/layers_pb2.pyi
jitxcore/_proto/local_pb2.py
jitxcore/_proto/local_pb2.pyi
jitxcore/_proto/mapping_pb2.py
jitxcore/_proto/mapping_pb2.pyi
jitxcore/_proto/material_pb2.py
jitxcore/_proto/material_pb2.pyi
jitxcore/_proto/module_pb2.py
jitxcore/_proto/module_pb2.pyi
jitxcore/_proto/nets_pb2.py
jitxcore/_proto/nets_pb2.pyi
jitxcore/_proto/pad_pb2.py
jitxcore/_proto/pad_pb2.pyi
jitxcore/_proto/pin_assignment_pb2.py
jitxcore/_proto/pin_assignment_pb2.pyi
jitxcore/_proto/ports_pb2.py
jitxcore/_proto/ports_pb2.pyi
jitxcore/_proto/routing_pb2.py
jitxcore/_proto/routing_pb2.pyi
jitxcore/_proto/routing_structures_pb2.py
jitxcore/_proto/routing_structures_pb2.pyi
jitxcore/_proto/rules_pb2.py
jitxcore/_proto/rules_pb2.pyi
jitxcore/_proto/schematic_pb2.py
jitxcore/_proto/schematic_pb2.pyi
jitxcore/_proto/shapes_pb2.py
jitxcore/_proto/shapes_pb2.pyi
jitxcore/_proto/signal_models_pb2.py
jitxcore/_proto/signal_models_pb2.pyi
jitxcore/_proto/stackup_pb2.py
jitxcore/_proto/stackup_pb2.pyi
jitxcore/_proto/symbol_pb2.py
jitxcore/_proto/symbol_pb2.pyi
jitxcore/_proto/via_patterns_pb2.py
jitxcore/_proto/via_patterns_pb2.pyi
jitxcore/_proto/via_pb2.py
jitxcore-4.0.0.dist-info/METADATA
jitxcore-4.0.0.dist-info/WHEEL
jitxcore-4.0.0.dist-info/RECORD
